README.rst
setup.py
radicale_auth_sasl/__init__.py
radicale_auth_sasl.egg-info/PKG-INFO
radicale_auth_sasl.egg-info/SOURCES.txt
radicale_auth_sasl.egg-info/dependency_links.txt
radicale_auth_sasl.egg-info/top_level.txt