Metadata-Version: 1.0
Name: radicale-auth-sasl
Version: 0.1.0
Summary: radicale plugin for sasl authentication
Home-page: https://github.com/paulfariello/radicale-auth-sasl
Author: Paul Fariello
Author-email: paul@fariello.eu
License: UNKNOWN
Platform: UNKNOWN
